solace_ai_connector/__init__.py
solace_ai_connector/logging.py
solace_ai_connector/main.py
solace_ai_connector/solace_ai_connector.py
solace_ai_connector/common/__init__.py
solace_ai_connector/common/config_validation.py
solace_ai_connector/common/event.py
solace_ai_connector/common/exceptions.py
solace_ai_connector/common/invoke_functions.py
solace_ai_connector/common/log.py
solace_ai_connector/common/logging_config.py
solace_ai_connector/common/message.py
solace_ai_connector/common/monitoring.py
solace_ai_connector/common/session_config.py
solace_ai_connector/common/trace_message.py
solace_ai_connector/common/utils.py
solace_ai_connector/common/messaging/__init__.py
solace_ai_connector/common/messaging/dev_broker_messaging.py
solace_ai_connector/common/messaging/messaging.py
solace_ai_connector/common/messaging/messaging_builder.py
solace_ai_connector/common/messaging/solace_messaging.py
solace_ai_connector/components/__init__.py
solace_ai_connector/components/component_base.py
solace_ai_connector/components/general/__init__.py
solace_ai_connector/components/general/aggregate.py
solace_ai_connector/components/general/assembly.py
solace_ai_connector/components/general/delay.py
solace_ai_connector/components/general/iterate.py
solace_ai_connector/components/general/message_filter.py
solace_ai_connector/components/general/parser.py
solace_ai_connector/components/general/pass_through.py
solace_ai_connector/components/general/user_processor.py
solace_ai_connector/components/general/db/__init__.py
solace_ai_connector/components/general/db/mongo/__init__.py
solace_ai_connector/components/general/db/mongo/mongo_base.py
solace_ai_connector/components/general/db/mongo/mongo_handler.py
solace_ai_connector/components/general/db/mongo/mongo_insert.py
solace_ai_connector/components/general/db/mongo/mongo_search.py
solace_ai_connector/components/general/db/sql/mysql_database_handler.py
solace_ai_connector/components/general/db/sql/postgres_database_handler.py
solace_ai_connector-3.2.0.dist-info/METADATA
solace_ai_connector-3.2.0.dist-info/WHEEL
solace_ai_connector-3.2.0.dist-info/entry_points.txt
solace_ai_connector-3.2.0.dist-info/licenses/LICENSE
solace_ai_connector-3.2.0.dist-info/RECORD
